yaqd_control/__init__.py
yaqd_control/__main__.py
yaqd_control/__version__.py
yaqd_control/_cache.py
yaqd_control/_daemon_data.py
yaqd_control/_enablement.py
yaqd_control/_list.py
yaqd_control/_scan.py
yaqd_control/_status.py
yaqd_control/bin/nssm.exe
yaqd_control-2023.6.0.dist-info/METADATA
yaqd_control-2023.6.0.dist-info/WHEEL
yaqd_control-2023.6.0.dist-info/entry_points.txt
yaqd_control-2023.6.0.dist-info/licenses/LICENSE
yaqd_control-2023.6.0.dist-info/RECORD
